{
    "title": "Search Dashboard",
    "_base": "dashboard",
  "annotations": {
    "list": [
      {
        "datasource": "-- Grafana --",
        "enable": true,
        "hide": false,
        "iconColor": "#ffffff",
        "limit": 500,
        "matchAny": true,
        "name": "Topology",
        "showIn": 0,
        "tags": [
          "topology"
        ],
        "type": "tags"
      },
      {
        "datasource": "-- Grafana --",
        "enable": true,
        "hide": false,
        "iconColor": "#115fd4",
        "limit": 500,
        "matchAny": true,
        "name": "Buckets",
        "showIn": 0,
        "tags": [
          "buckets"
        ],
        "type": "tags"
      }
    ]
  },
  "_panels": [
          {
            "title": "fts_num_bytes_used_ram",
            "_base": "panel",
            "_targets": [
              {
                "datasource": "{data-source-name}",
                "expr": "fts_num_bytes_used_ram",
                "legendFormat": "{data-source-name} fts_num_bytes_used_ram",
                "_base": "target"
              }
            ]
          },
          {
            "title": "fts_num_bytes_used_ram_c",
            "_base": "panel",
            "_targets": [
              {
                "datasource": "{data-source-name}",
                "expr": "fts_num_bytes_used_ram_c",
                "legendFormat": "{data-source-name} fts_num_bytes_used_ram_c",
                "_base": "target"
              }
            ]
          },
          {
            "title": "fts_curr_batches_blocked_by_herder",
            "_base": "panel",
            "_targets": [
              {
                "datasource": "{data-source-name}",
                "expr": "fts_curr_batches_blocked_by_herder",
                "legendFormat": "{data-source-name} fts_curr_batches_blocked_by_herder",
                "_base": "target"
              }
            ]
          },
          {
            "title": "fts_tot_queryreject_on_memquota",
            "_base": "panel",
            "_targets": [
              {
                "datasource": "{data-source-name}",
                "expr": "fts_tot_queryreject_on_memquota",
                "legendFormat": "{data-source-name} fts_tot_queryreject_on_memquota",
                "_base": "target"
              }
            ]
          },
          {
            "title": "fts_tot_grpc_queryreject_on_memquota",
            "_base": "panel",
            "_targets": [
              {
                "datasource": "{data-source-name}",
                "expr": "fts_tot_grpc_queryreject_on_memquota",
                "legendFormat": "{data-source-name} fts_tot_grpc_queryreject_on_memquota",
                "_base": "target"
              }
            ]
          },
          {
            "title": "fts_total_queries_rejected_by_herder",
            "_base": "panel",
            "_targets": [
              {
                "datasource": "{data-source-name}",
                "expr": "fts_total_queries_rejected_by_herder",
                "legendFormat": "{data-source-name} fts_total_queries_rejected_by_herder",
                "_base": "target"
              }
            ]
          },
          {
            "title": "fts_batch_bytes_added",
            "_base": "panel",
            "_targets": [
              {
                "datasource": "{data-source-name}",
                "expr": "fts_batch_bytes_added",
                "legendFormat": "{data-source-name} fts_batch_bytes_added",
                "_base": "target"
              }
            ]
          },
          {
            "title": "fts_batch_bytes_removed",
            "_base": "panel",
            "_targets": [
              {
                "datasource": "{data-source-name}",
                "expr": "fts_batch_bytes_removed",
                "legendFormat": "{data-source-name} fts_batch_bytes_removed",
                "_base": "target"
              }
            ]
          },
          {
            "title": "fts_num_batches_introduced",
            "_base": "panel",
            "_targets": [
              {
                "datasource": "{data-source-name}",
                "expr": "fts_num_batches_introduced",
                "legendFormat": "{data-source-name} fts_num_batches_introduced",
                "_base": "target"
              }
            ]
          },
          {
            "title": "fts_num_files_on_disk",
            "_base": "panel",
            "_targets": [
              {
                "datasource": "{data-source-name}",
                "expr": "fts_num_files_on_disk",
                "legendFormat": "{data-source-name} fts_num_files_on_disk",
                "_base": "target"
              }
            ]
          },
          {
            "title": "fts_pct_cpu_gc",
            "_base": "panel",
            "_targets": [
              {
                "datasource": "{data-source-name}",
                "expr": "fts_pct_cpu_gc",
                "legendFormat": "{data-source-name} fts_pct_cpu_gc",
                "_base": "target"
              }
            ]
          },
          {
            "title": "fts_total_gc",
            "_base": "panel",
            "_targets": [
              {
                "datasource": "{data-source-name}",
                "expr": "fts_total_gc",
                "legendFormat": "{data-source-name} fts_total_gc",
                "_base": "target"
              }
            ]
          },
          {
            "title": "fts_doc_count",
            "_base": "panel",
            "_targets": [
              {
                "datasource": "{data-source-name}",
                "expr": "fts_doc_count",
                "legendFormat": "{data-source-name} fts_doc_count",
                "_base": "target"
              }
            ]
          },
          {
            "title": "fts_total_queries",
            "_base": "panel",
            "_targets": [
              {
                "datasource": "{data-source-name}",
                "expr": "fts_total_queries",
                "legendFormat": "{data-source-name} fts_total_queries",
                "_base": "target"
              }
            ]
          },
          {
            "title": "fts_total_grpc_internal_queries",
            "_base": "panel",
            "_targets": [
              {
                "datasource": "{data-source-name}",
                "expr": "fts_total_grpc_internal_queries",
                "legendFormat": "{data-source-name} fts_total_grpc_internal_queries",
                "_base": "target"
              }
            ]
          },
          {
            "title": "fts_total_queries_error",
            "_base": "panel",
            "_targets": [
              {
                "datasource": "{data-source-name}",
                "expr": "fts_total_queries_error",
                "legendFormat": "{data-source-name} fts_total_queries_error",
                "_base": "target"
              }
            ]
          },
          {
            "title": "fts_total_queries_timeout",
            "_base": "panel",
            "_targets": [
              {
                "datasource": "{data-source-name}",
                "expr": "fts_total_queries_timeout",
                "legendFormat": "{data-source-name} fts_total_queries_timeout",
                "_base": "target"
              }
            ]
          },
          {
            "title": "fts_total_queries_slow",
            "_base": "panel",
            "_targets": [
              {
                "datasource": "{data-source-name}",
                "expr": "fts_total_queries_slow",
                "legendFormat": "{data-source-name} fts_total_queries_slow",
                "_base": "target"
              }
            ]
          },
          {
            "title": "fts_num_bytes_used_disk",
            "_base": "panel",
            "_targets": [
              {
                "datasource": "{data-source-name}",
                "expr": "fts_num_bytes_used_disk",
                "legendFormat": "{data-source-name} fts_num_bytes_used_disk",
                "_base": "target"
              }
            ]
          },
          {
            "title": "fts_num_knn_search_requests",
            "_base": "panel",
            "_targets": [
              {
                "datasource": "{data-source-name}",
                "expr": "fts_num_knn_search_requests",
                "legendFormat": "{data-source-name} fts_num_knn_search_requests",
                "_base": "target"
              }
            ]
          },
          {
            "title": "fts_total_knn_searches",
            "_base": "panel",
            "_targets": [
              {
                "datasource": "{data-source-name}",
                "expr": "fts_total_knn_searches",
                "legendFormat": "{data-source-name} fts_total_knn_searches",
                "_base": "target"
              }
            ]
          },
          {
            "title": "fts_total_bytes_indexed",
            "_base": "panel",
            "_targets": [
              {
                "datasource": "{data-source-name}",
                "expr": "fts_total_bytes_indexed",
                "legendFormat": "{data-source-name} fts_total_bytes_indexed",
                "_base": "target"
              }
            ]
          },
          {
            "title": "fts_num_mutations_to_index",
            "_base": "panel",
            "_targets": [
              {
                "datasource": "{data-source-name}",
                "expr": "fts_num_mutations_to_index",
                "legendFormat": "{data-source-name} fts_num_mutations_to_index",
                "_base": "target"
              }
            ]
          },
          {
            "title": "fts_num_recs_to_persist",
            "_base": "panel",
            "_targets": [
              {
                "datasource": "{data-source-name}",
                "expr": "fts_num_recs_to_persist",
                "legendFormat": "{data-source-name} fts_num_recs_to_persist",
                "_base": "target"
              }
            ]
          },
          {
            "title": "fts_num_file_merge_ops",
            "_base": "panel",
            "_targets": [
              {
                "datasource": "{data-source-name}",
                "expr": "fts_num_file_merge_ops",
                "legendFormat": "{data-source-name} fts_num_file_merge_ops",
                "_base": "target"
              }
            ]
          },
          {
            "title": "fts_num_mem_merge_ops",
            "_base": "panel",
            "_targets": [
              {
                "datasource": "{data-source-name}",
                "expr": "fts_num_mem_merge_ops",
                "legendFormat": "{data-source-name} fts_num_mem_merge_ops",
                "_base": "target"
              }
            ]
          },
          {
            "title": "fts_total_term_searchers",
            "_base": "panel",
            "_targets": [
              {
                "datasource": "{data-source-name}",
                "expr": "fts_total_term_searchers",
                "legendFormat": "{data-source-name} fts_total_term_searchers",
                "_base": "target"
              }
            ]
          },
          {
            "title": "fts_total_term_searchers_finished",
            "_base": "panel",
            "_targets": [
              {
                "datasource": "{data-source-name}",
                "expr": "fts_total_term_searchers_finished",
                "legendFormat": "{data-source-name} fts_total_term_searchers_finished",
                "_base": "target"
              }
            ]
          }
    ]
  }
